easynas/__init__.py
easynas/genetic_algorithm.py
easynas/model_generation.py
easynas-0.2.1.dist-info/LICENSE.txt
easynas-0.2.1.dist-info/METADATA
easynas-0.2.1.dist-info/WHEEL
easynas-0.2.1.dist-info/top_level.txt
easynas-0.2.1.dist-info/RECORD
