Metadata-Version: 2.1
Name: easynas
Version: 0.2.1
Summary: A simple utility for generating CNN architectures automatically, using genetic algorithms.
Home-page: https://github.com/erap129/EasyNAS
Author: Elad Rapaport
Author-email: erap129@gmail.com
License: MIT
Download-URL: https://github.com/erap129/EasyNAS/archive/0.1.tar.gz
Keywords: NAS,GENETIC,CNN
Platform: UNKNOWN
Classifier: Development Status :: 3 - Alpha
Classifier: Intended Audience :: Developers
Classifier: Topic :: Software Development :: Build Tools
Classifier: License :: OSI Approved :: MIT License
Classifier: Programming Language :: Python :: 3
Requires-Dist: tqdm
Requires-Dist: torch
Requires-Dist: numpy
Requires-Dist: pytorch-lightning
Requires-Dist: scikit-learn
Requires-Dist: pyeasyga
